{
    "rules": [
        {
            "field": "synth__area__stdcell__count",
            "value": 17184,
            "compare": "=="
        },
        {
            "field": "constraints__clocks__count",
            "value": 1,
            "compare": "=="
        },
        {
            "field": "placeopt__area__instance__area",
            "value": 151146,
            "compare": "<="
        },
        {
            "field": "placeopt__area__instance__count",
            "value": 19206,
            "compare": "<="
        },
        {
            "field": "cts__timing__tns__total__pre_repair",
            "value": -250,
            "compare": ">="
        },
        {
            "field": "cts__timing__wns__worst__pre_repair",
            "value": -250,
            "compare": ">="
        },
        {
            "field": "cts__timing__ws__worst__pre_repair",
            "value": 21,
            "compare": "<="
        },
        {
            "field": "cts__timing__tns__total",
            "value": -465,
            "compare": ">="
        },
        {
            "field": "cts__timing__wns__worst",
            "value": -21,
            "compare": ">="
        },
        {
            "field": "cts__timing__ws__worst",
            "value": -21,
            "compare": ">="
        },
        {
            "field": "globalroute__timing__tns__total",
            "value": -856,
            "compare": ">="
        },
        {
            "field": "globalroute__timing__ws__worst",
            "value": -21,
            "compare": ">="
        },
        {
            "field": "detailedroute__wirelength",
            "value": 965041,
            "compare": "<="
        },
        {
            "field": "detailedroute__errors__count",
            "value": 0,
            "compare": "<="
        },
        {
            "field": "detailedroute__drc__error__count",
            "value": 0,
            "compare": "<="
        },
        {
            "field": "finish__area",
            "value": 691548,
            "compare": "<="
        }
    ]
}