{
    "rules": [
        {
            "field": "synth__design__instance__area__stdcell",
            "value": 2560,
            "compare": "<="
        },
        {
            "field": "constraints__clocks__count",
            "value": 1,
            "compare": "=="
        },
        {
            "field": "placeopt__design__instance__area",
            "value": 2655,
            "compare": "<="
        },
        {
            "field": "placeopt__design__instance__count__stdcell",
            "value": 19923,
            "compare": "<="
        },
        {
            "field": "detailedplace__design__violations",
            "value": 0,
            "compare": "=="
        },
        {
            "field": "cts__timing__setup__ws",
            "value": -214.37,
            "compare": ">="
        },
        {
            "field": "cts__timing__setup__ws__pre_repair",
            "value": -496.68,
            "compare": ">="
        },
        {
            "field": "cts__timing__setup__ws__post_repair",
            "value": -496.68,
            "compare": ">="
        },
        {
            "field": "globalroute__timing__clock__slack",
            "value": -227.9,
            "compare": ">="
        },
        {
            "field": "globalroute__timing__setup__ws",
            "value": -227.9,
            "compare": ">="
        },
        {
            "field": "detailedroute__route__wirelength",
            "value": 81994,
            "compare": "<="
        },
        {
            "field": "detailedroute__route__drc_errors",
            "value": 0,
            "compare": "<="
        },
        {
            "field": "finish__timing__setup__ws",
            "value": -207.53,
            "compare": ">="
        },
        {
            "field": "finish__design__instance__area",
            "value": 6438,
            "compare": "<="
        }
    ]
}