{
    "rules": [
        {
            "field": "synth__design__instance__area__stdcell",
            "value": 268,
            "compare": "<="
        },
        {
            "field": "constraints__clocks__count",
            "value": 2,
            "compare": "=="
        },
        {
            "field": "placeopt__design__instance__area",
            "value": 1629579,
            "compare": "<="
        },
        {
            "field": "placeopt__design__instance__count__stdcell",
            "value": 114471,
            "compare": "<="
        },
        {
            "field": "detailedplace__design__violations",
            "value": 0,
            "compare": "=="
        },
        {
            "field": "cts__timing__setup__ws",
            "value": -0.79,
            "compare": ">="
        },
        {
            "field": "cts__timing__setup__ws__pre_repair",
            "value": -1.69,
            "compare": ">="
        },
        {
            "field": "cts__timing__setup__ws__post_repair",
            "value": -1.69,
            "compare": ">="
        },
        {
            "field": "globalroute__timing__setup__ws",
            "value": -1.07,
            "compare": ">="
        },
        {
            "field": "detailedroute__route__wirelength",
            "value": 7600787,
            "compare": "<="
        },
        {
            "field": "detailedroute__route__drc_errors",
            "value": 0,
            "compare": "<="
        },
        {
            "field": "finish__timing__setup__ws",
            "value": 0.0,
            "compare": ">="
        },
        {
            "field": "finish__design__instance__area",
            "value": 1655037,
            "compare": "<="
        }
    ]
}