{
    "rules": [
        {
            "field": "synth__design__instance__area__stdcell",
            "value": 290122,
            "compare": "<="
        },
        {
            "field": "constraints__clocks__count",
            "value": 1,
            "compare": "=="
        },
        {
            "field": "placeopt__design__instance__area",
            "value": 404222,
            "compare": "<="
        },
        {
            "field": "placeopt__design__instance__count__stdcell",
            "value": 620988,
            "compare": "<="
        },
        {
            "field": "detailedplace__design__violations",
            "value": 0,
            "compare": "=="
        },
        {
            "field": "cts__timing__setup__ws",
            "value": -816.91,
            "compare": ">="
        },
        {
            "field": "cts__timing__setup__ws__pre_repair",
            "value": -887.49,
            "compare": ">="
        },
        {
            "field": "cts__timing__setup__ws__post_repair",
            "value": -867.72,
            "compare": ">="
        },
        {
            "field": "cts__design__instance__count__hold_buffer",
            "value": 5249.2,
            "compare": "<="
        },
        {
            "field": "globalroute__timing__clock__slack",
            "value": -612.39,
            "compare": ">="
        },
        {
            "field": "globalroute__timing__setup__ws",
            "value": -612.39,
            "compare": ">="
        },
        {
            "field": "detailedroute__route__wirelength",
            "value": 18398734,
            "compare": "<="
        },
        {
            "field": "detailedroute__route__drc_errors",
            "value": 0,
            "compare": "<="
        },
        {
            "field": "finish__timing__setup__ws",
            "value": -22.63,
            "compare": ">="
        },
        {
            "field": "finish__design__instance__area",
            "value": 413732,
            "compare": "<="
        },
        {
            "field": "finish__timing__drv__max_slew",
            "value": 144,
            "compare": "<="
        },
        {
            "field": "finish__timing__drv__max_fanout",
            "value": 0,
            "compare": "<="
        },
        {
            "field": "finish__timing__drv__max_cap",
            "value": 1,
            "compare": "<="
        },
        {
            "field": "finish__timing__drv__setup_violation_count",
            "value": 1,
            "compare": "<="
        },
        {
            "field": "finish__timing__drv__hold_violation_count",
            "value": 0,
            "compare": "<="
        }
    ]
}