{
  "constraints__clocks__count": 0,
  "constraints__clocks__details": [],
  "cts__design__instance__count__hold_buffer": "ERR",
  "cts__design__instance__count__setup_buffer": "ERR",
  "detailedplace__cpu__total": "ERR",
  "detailedplace__design__violations": "ERR",
  "detailedplace__mem__peak": "ERR",
  "detailedplace__runtime__total": "ERR",
  "finish__cpu__total": "ERR",
  "finish__mem__peak": "ERR",
  "finish__runtime__total": "ERR",
  "finish__timing__drv__hold_violation_count": "ERR",
  "finish__timing__drv__setup_violation_count": "ERR",
  "finish__timing__wns_percent_delay": "ERR",
  "floorplan__cpu__total": "ERR",
  "floorplan__mem__peak": "ERR",
  "floorplan__runtime__total": "ERR",
  "globalroute__timing__clock__slack": "ERR",
  "placeopt__cpu__total": "ERR",
  "placeopt__mem__peak": "ERR",
  "placeopt__runtime__total": "ERR",
  "run__flow__design": "chameleon_hier",
  "run__flow__generate_date": "2022-09-07 09:29",
  "run__flow__metrics_version": "Metrics_2.1.2",
  "run__flow__openroad_commit": "N/A",
  "run__flow__openroad_version": "v2.0-4871-g6fd2fefc4",
  "run__flow__platform": "sky130hd",
  "run__flow__platform_commit": "8aa9f2dd46129f2c0a670095c93e8c9477cb1ccc",
  "run__flow__scripts_commit": "8aa9f2dd46129f2c0a670095c93e8c9477cb1ccc",
  "run__flow__uuid": "94b13189-a5bf-4f53-b0a0-de252bcd47a2",
  "run__flow__variant": "base",
  "synth__cpu__total": 9.45,
  "synth__design__instance__area__stdcell": 24429.68,
  "synth__design__instance__count__stdcell": 1897.0,
  "synth__mem__peak": 69768.0,
  "synth__runtime__total": "0:10.31",
  "total_time": "ERR"
}